seqwalk/.DS_Store
seqwalk/.ipynb_checkpoints/playground-checkpoint.ipynb
seqwalk/__init__.py
seqwalk/analysis.py
seqwalk/design.py
seqwalk/filtering.py
seqwalk/generation.py
seqwalk/io.py
seqwalk/prebuilt_libs/__init__.py
seqwalk/prebuilt_libs/kishi2018.txt
seqwalk-0.3.3.dist-info/LICENSE
seqwalk-0.3.3.dist-info/WHEEL
seqwalk-0.3.3.dist-info/METADATA
seqwalk-0.3.3.dist-info/RECORD
