Metadata-Version: 2.1
Name: seqwalk
Version: 0.3.3
Summary: Design orthogonal DNA sequences
License: MIT
Author: Gokul Gowri
Requires-Python: >=3.8,<4.0
Classifier: License :: OSI Approved :: MIT License
Classifier: Programming Language :: Python :: 3
Classifier: Programming Language :: Python :: 3.10
Classifier: Programming Language :: Python :: 3.8
Classifier: Programming Language :: Python :: 3.9
Requires-Dist: numpy (>=1.23.0,<2.0.0)
